aiohttp_ac_hipchat/__init__.py
aiohttp_ac_hipchat/addon.py
aiohttp_ac_hipchat/addon_app.py
aiohttp_ac_hipchat/cache.py
aiohttp_ac_hipchat/installable.py
aiohttp_ac_hipchat/oauth2.py
aiohttp_ac_hipchat/room_client.py
aiohttp_ac_hipchat/store.py
aiohttp_ac_hipchat/util.py
aiohttp_ac_hipchat/webapp.py
aiohttp_ac_hipchat/websocket.py
aiohttp_ac_hipchat/test/__init__.py
aiohttp_ac_hipchat-0.4.5.dist-info/DESCRIPTION.rst
aiohttp_ac_hipchat-0.4.5.dist-info/METADATA
aiohttp_ac_hipchat-0.4.5.dist-info/RECORD
aiohttp_ac_hipchat-0.4.5.dist-info/WHEEL
aiohttp_ac_hipchat-0.4.5.dist-info/metadata.json
aiohttp_ac_hipchat-0.4.5.dist-info/top_level.txt
aiolocals/__init__.py
aiolocals/local.py
aiolocals/log.py
aiolocals/middleware.py
