Metadata-Version: 2.0
Name: aiohttp-ac-hipchat
Version: 0.4.5
Summary: Aiohttp extension to support Atlassian Connect for HipChat
Home-page: https://bitbucket.org/atlassianlabs/aiohttp_ac_hipchat
Author: Julien Hoarau
Author-email: julien@atlassian.com
License: APLv2
Platform: any
Classifier: Environment :: Web Environment
Classifier: Intended Audience :: Developers
Classifier: License :: OSI Approved :: BSD License
Classifier: Operating System :: OS Independent
Classifier: Programming Language :: Python
Classifier: Topic :: Internet :: WWW/HTTP :: Dynamic Content
Classifier: Topic :: Software Development :: Libraries :: Python Modules
Requires-Dist: PyJWT
Requires-Dist: aiohttp
Requires-Dist: asyncio-redis
Requires-Dist: motor
